{
  "id": "relationship:wikipedia-taj-mahal--big-mama-thornton",
  "slug": "wikipedia-taj-mahal--big-mama-thornton",
  "entityAId": "entity:taj-mahal",
  "entityBId": "entity:big-mama-thornton",
  "relationshipType": "provisional_unspecified",
  "orientation": "undetermined",
  "evidenceCategory": "contextual_or_inferential",
  "explanation": "A Wikipedia biography explicitly connects Taj Mahal and Willie Mae “Big Mama” Thornton in a career, recording, repertoire, family, or scene context. The precise relationship type awaits editorial review.",
  "citationIds": ["source:wikipedia-biography-taj-mahal"],
  "reviewStatus": "provisional",
  "disputeStatus": "none",
  "curatorNote": "Automatically discovered from explicit linked mentions in Wikipedia biography text (taj-mahal@1363505672:26). Verify the cited page context and an independent source before review."
}
