{
  "id": "relationship:wikipedia-joe-willie-wilkins--mose-vinson",
  "slug": "wikipedia-joe-willie-wilkins--mose-vinson",
  "entityAId": "entity:joe-willie-wilkins",
  "entityBId": "entity:mose-vinson",
  "relationshipType": "provisional_unspecified",
  "orientation": "undetermined",
  "evidenceCategory": "contextual_or_inferential",
  "explanation": "A Wikipedia biography explicitly connects Joe Willie Wilkins and Mose Vinson in a career, recording, repertoire, family, or scene context. The precise relationship type awaits editorial review.",
  "citationIds": [
    "source:wikipedia-biography-joe-willie-wilkins",
    "source:wikipedia-biography-mose-vinson"
  ],
  "reviewStatus": "provisional",
  "disputeStatus": "none",
  "curatorNote": "Automatically discovered from explicit linked mentions in Wikipedia biography text (joe-willie-wilkins@1357829212:5, mose-vinson@1323738066:3). Verify the cited page context and an independent source before review."
}
